parquet_datastore_utils/__init__.py
parquet_datastore_utils/cleaner.py
parquet_datastore_utils/read_write_delete.py
parquet_datastore_utils-0.1.14.dist-info/LICENSE
parquet_datastore_utils-0.1.14.dist-info/METADATA
parquet_datastore_utils-0.1.14.dist-info/WHEEL
parquet_datastore_utils-0.1.14.dist-info/RECORD
